OpenConnectome/__init__.py
OpenConnectome/openconnectome.py
openconnectome-0.0.11.dist-info/LICENSE
openconnectome-0.0.11.dist-info/METADATA
openconnectome-0.0.11.dist-info/WHEEL
openconnectome-0.0.11.dist-info/top_level.txt
openconnectome-0.0.11.dist-info/RECORD
