Metadata-Version: 2.1
Name: openconnectome
Version: 0.0.11
Summary: Brain Graph Management and Numerical Model Simulations on Brains
Home-page: https://github.com/Stefano314/OpenConnectome
Author: Stefano Bianchi
Author-email: stefanobianchi314@gmail.com
License: CC BY-NC 4.0
Classifier: Development Status :: 3 - Alpha
Classifier: Intended Audience :: Science/Research
Classifier: Programming Language :: Python :: 3.10
Classifier: Topic :: Scientific/Engineering :: Mathematics
Classifier: Topic :: Scientific/Engineering :: Bio-Informatics
Classifier: Topic :: Scientific/Engineering :: Medical Science Apps.
License-File: LICENSE
Requires-Dist: numpy >=1.23
Requires-Dist: matplotlib >=3.5.2
Requires-Dist: pandas >=1.4.2
Requires-Dist: networkx >=2.8.5
Requires-Dist: scipy >=1.8.1
Requires-Dist: tqdm >=4.64.0
